[
    {
        "title": "Die ältere Dame in Berlin hieß Anna.",
        "tr": true,
        "fle": false
    },
    {
        "title": "Der junge Mann aus Italien sprach fließend Deutsch.",
        "tr": false,
        "fle": true
    },
    {
        "title": "Anna und Marco besuchten den Berliner Dom an diesem Tag.",
        "tr": false,
        "fle": true
    },
    {
        "title": "Die Begegnung zwischen Anna und Marco fand in München statt.",
        "tr": false,
        "fle": true
    },
    {
        "title": "Anna und Marco tauschten keine Kontaktdaten aus.",
        "tr": false,
        "fle": true
    }      
]